src/__init__.py
dux-0.1.0.dist-info/METADATA
dux-0.1.0.dist-info/WHEEL
dux-0.1.0.dist-info/top_level.txt
dux-0.1.0.dist-info/RECORD
